wallcrop/_version.py
wallcrop/create_monitors_file.py
wallcrop/wallcrop.py
wallcrop/wallswitch.py
wallcrop-0.0.6.dist-info/LICENSE
wallcrop-0.0.6.dist-info/METADATA
wallcrop-0.0.6.dist-info/WHEEL
wallcrop-0.0.6.dist-info/entry_points.txt
wallcrop-0.0.6.dist-info/top_level.txt
wallcrop-0.0.6.dist-info/RECORD
