Metadata-Version: 2.1
Name: wallcrop
Version: 0.0.6
Summary: A tool for cropping an image into smaller images for use as individual desktop wallpapers
Author-email: Max Weidauer <weidauer@campus.tu-berlin.de>
Maintainer-email: Max Weidauer <weidauer@campus.tu-berlin.de>
License: GNU GENERAL PUBLIC LICENSE
Project-URL: Github, https://github.com/themaxw/wallcrop
Project-URL: Issues, https://github.com/themaxw/wallcrop/issues
Requires-Python: >=3.10
License-File: LICENSE
Requires-Dist: pillow
Requires-Dist: click
Requires-Dist: pyYAML
Requires-Dist: tqdm
